constrictor/__init__.py
constrictor/blueprint_loader.py
constrictor/cli.py
constrictor/tests/__init__.py
constrictor/tests/test_constrictor.py
constrictor/tests/test_performance.py
constrictor_framework-1.0.0.dist-info/METADATA
constrictor_framework-1.0.0.dist-info/WHEEL
constrictor_framework-1.0.0.dist-info/entry_points.txt
constrictor_framework-1.0.0.dist-info/top_level.txt
constrictor_framework-1.0.0.dist-info/RECORD
